<?xml version='1.0' encoding='utf-8' standalone='no'?>
<move>
	<name>Overheat</name>
	<move_records>
		<move_record>
			<games>
				<game>Pokemon Red</game>
				<game>Pokemon Blue</game>
				<game>Pokemon Yellow</game>
				<game>Pokemon Gold</game>
				<game>Pokemon Silver</game>
				<game>Pokemon Crystal</game>
				<game>Pokemon Ruby</game>
				<game>Pokemon Sapphire</game>
				<game>Pokemon Emerald</game>
				<game>Pokemon FireRed</game>
				<game>Pokemon LeafGreen</game>
				<game>Pokemon Diamond</game>
				<game>Pokemon Pearl</game>
				<game>Pokemon Platinum</game>
				<game>Pokemon HeartGold</game>
				<game>Pokemon SoulSilver</game>
				<game>Pokemon Black</game>
				<game>Pokemon White</game>
				<game>Pokemon Black 2</game>
				<game>Pokemon White 2</game>
			</games>
			<move_definition>
				<generation>3</generation>
				<type>Fire</type>
				<base_power>140</base_power>
				<power_points>5</power_points>
				<accuracy>90</accuracy>
				<priority>0</priority>
				<damage_category>Special</damage_category>
				<effect/>
				<effect_chance>100</effect_chance>
				<description>Lowers the user's Special Attack by two stages after inflicting damage.</description>
			</move_definition>
		</move_record>
		<move_record>
			<games>
				<game>Pokemon X</game>
				<game>Pokemon Y</game>
				<game>Pokemon Omega Ruby</game>
				<game>Pokemon Alpha Sapphire</game>
				<game>Pokemon Sun</game>
				<game>Pokemon Moon</game>
				<game>Pokemon Ultra Sun</game>
				<game>Pokemon Ultra Moon</game>
				<game>Pokemon Sword</game>
				<game>Pokemon Shield</game>
			</games>
			<move_definition>
				<generation>3</generation>
				<type>Fire</type>
				<base_power>130</base_power>
				<power_points>5</power_points>
				<accuracy>90</accuracy>
				<priority>0</priority>
				<damage_category>Special</damage_category>
				<effect/>
				<effect_chance>100</effect_chance>
				<description>Lowers the user's Special Attack by two stages after inflicting damage.</description>
			</move_definition>
		</move_record>
		<move_record>
			<games>
				<game>Pokemon Emerald Kaizo</game>
			</games>
			<move_definition>
				<generation>3</generation>
				<type>Fire</type>
				<base_power>120</base_power>
				<power_points>16</power_points>
				<accuracy>100</accuracy>
				<priority>0</priority>
				<damage_category>Special</damage_category>
				<effect/>
				<effect_chance>100</effect_chance>
				<description>User receives 1/3 the damage inflicted in recoil.</description>
			</move_definition>
		</move_record>
	</move_records>
	<tm_records>
		<tm_record>
			<games>
				<game>Pokemon Ruby</game>
				<game>Pokemon Sapphire</game>
				<game>Pokemon Emerald</game>
			</games>
			<tm_definition>
				<number>50</number>
				<location>Prize for defeating Flannery</location>
			</tm_definition>
		</tm_record>
		<tm_record>
			<games>
				<game>Pokemon FireRed</game>
				<game>Pokemon LeafGreen</game>
			</games>
			<tm_definition>
				<number>50</number>
				<location>Victory Road</location>
			</tm_definition>
		</tm_record>
		<tm_record>
			<games>
				<game>Pokemon Diamond</game>
				<game>Pokemon Pearl</game>
				<game>Pokemon Platinum</game>
			</games>
			<tm_definition>
				<number>50</number>
				<location>Stark Mountain</location>
			</tm_definition>
		</tm_record>
		<tm_record>
			<games>
				<game>Pokemon HeartGold</game>
				<game>Pokemon SoulSilver</game>
			</games>
			<tm_definition>
				<number>50</number>
				<location>Prize for defeating Blaine</location>
			</tm_definition>
		</tm_record>
		<tm_record>
			<games>
				<game>Pokemon Black</game>
				<game>Pokemon White</game>
			</games>
			<tm_definition>
				<number>50</number>
				<location>Route 11</location>
			</tm_definition>
		</tm_record>
		<tm_record>
			<games>
				<game>Pokemon Black 2</game>
				<game>Pokemon White 2</game>
			</games>
			<tm_definition>
				<number>50</number>
				<location>N's Castle</location>
			</tm_definition>
		</tm_record>
		<tm_record>
			<games>
				<game>Pokemon X</game>
				<game>Pokemon Y</game>
			</games>
			<tm_definition>
				<number>50</number>
				<location>Kiloude City Poké Mart</location>
				<cost>$80,000</cost>
			</tm_definition>
		</tm_record>
		<tm_record>
			<games>
				<game>Pokemon Omega Ruby</game>
				<game>Pokemon Alpha Sapphire</game>
			</games>
			<tm_definition>
				<number>50</number>
				<location>Prize for defeating Flannery</location>
			</tm_definition>
		</tm_record>
		<tm_record>
			<games>
				<game>Pokemon Sun</game>
				<game>Pokemon Moon</game>
				<game>Pokemon Ultra Sun</game>
				<game>Pokemon Ultra Moon</game>
			</games>
			<tm_definition>
				<number>50</number>
				<location>Poni Meadow</location>
			</tm_definition>
		</tm_record>
	</tm_records>
</move>
