<?xml version='1.0' encoding='utf-8' standalone='no'?>
<pokemon_tm_sets>
    <name>Coalossal</name>
    <tm_sets>
        <tm_set>
            <games>
                <game>Pokemon Sword</game>
                <game>Pokemon Shield</game>
            </games>
            <tmset_moves>
                <tmset_move>Mega Punch</tmset_move>
                <tmset_move>Mega Kick</tmset_move>
                <tmset_move>Fire Punch</tmset_move>
                <tmset_move>Hyper Beam</tmset_move>
                <tmset_move>Giga Impact</tmset_move>
                <tmset_move>Solar Beam</tmset_move>
                <tmset_move>Fire Spin</tmset_move>
                <tmset_move>Dig</tmset_move>
                <tmset_move>Reflect</tmset_move>
                <tmset_move>Rest</tmset_move>
                <tmset_move>Rock Slide</tmset_move>
                <tmset_move>Snore</tmset_move>
                <tmset_move>Protect</tmset_move>
                <tmset_move>Attract</tmset_move>
                <tmset_move>Sandstorm</tmset_move>
                <tmset_move>Facade</tmset_move>
                <tmset_move>Rock Tomb</tmset_move>
                <tmset_move>Sand Tomb</tmset_move>
                <tmset_move>Rock Blast</tmset_move>
                <tmset_move>Round</tmset_move>
                <tmset_move>Bulldoze</tmset_move>
                <tmset_move>Body Slam</tmset_move>
                <tmset_move>Flamethrower</tmset_move>
                <tmset_move>Earthquake</tmset_move>
                <tmset_move>Fire Blast</tmset_move>
                <tmset_move>Substitute</tmset_move>
                <tmset_move>Spikes</tmset_move>
                <tmset_move>Endure</tmset_move>
                <tmset_move>Sleep Talk</tmset_move>
                <tmset_move>Heat Wave</tmset_move>
                <tmset_move>Overheat</tmset_move>
                <tmset_move>Iron Defense</tmset_move>
                <tmset_move>Gyro Ball</tmset_move>
                <tmset_move>Flare Blitz</tmset_move>
                <tmset_move>Earth Power</tmset_move>
                <tmset_move>Iron Head</tmset_move>
                <tmset_move>Stone Edge</tmset_move>
                <tmset_move>Stealth Rock</tmset_move>
                <tmset_move>Heavy Slam</tmset_move>
                <tmset_move>Scald</tmset_move>
                <tmset_move>Heat Crash</tmset_move>
                <tmset_move>High Horsepower</tmset_move>
                <tmset_move>Body Press</tmset_move>
                <tmset_move>Will-O-Wisp</tmset_move>
                <tmset_move>Self-Destruct</tmset_move>
            </tmset_moves>
        </tm_set>
    </tm_sets>
</pokemon_tm_sets>
