<?xml version='1.0' encoding='utf-8' standalone='no'?>
<pokemon_learnsets>
	<name>Linoone</name>
	<learnsets>
		<learnset>
			<games>
				<game>Pokemon Ruby</game>
				<game>Pokemon Sapphire</game>
				<game>Pokemon Emerald</game>
				<game>Pokemon FireRed</game>
				<game>Pokemon LeafGreen</game>
			</games>
			<learnset_moves>
				<learnset_move>
					<name>Headbutt</name>
					<level>1</level>
				</learnset_move>
				<learnset_move>
					<name>Tackle</name>
					<level>1</level>
				</learnset_move>
				<learnset_move>
					<name>Tail Whip</name>
					<level>1</level>
				</learnset_move>
				<learnset_move>
					<name>Growl</name>
					<level>1</level>
				</learnset_move>
				<learnset_move>
					<name>Tail Whip</name>
					<level>5</level>
				</learnset_move>
				<learnset_move>
					<name>Headbutt</name>
					<level>9</level>
				</learnset_move>
				<learnset_move>
					<name>Sand Attack</name>
					<level>13</level>
				</learnset_move>
				<learnset_move>
					<name>Odor Sleuth</name>
					<level>17</level>
				</learnset_move>
				<learnset_move>
					<name>Mud Sport</name>
					<level>23</level>
				</learnset_move>
				<learnset_move>
					<name>Fury Swipes</name>
					<level>29</level>
				</learnset_move>
				<learnset_move>
					<name>Covet</name>
					<level>35</level>
				</learnset_move>
				<learnset_move>
					<name>Slash</name>
					<level>41</level>
				</learnset_move>
				<learnset_move>
					<name>Rest</name>
					<level>47</level>
				</learnset_move>
				<learnset_move>
					<name>Belly Drum</name>
					<level>53</level>
				</learnset_move>
			</learnset_moves>
		</learnset>
		<learnset>
			<games>
				<game>Pokemon Diamond</game>
				<game>Pokemon Pearl</game>
				<game>Pokemon Platinum</game>
				<game>Pokemon HeartGold</game>
				<game>Pokemon SoulSilver</game>
			</games>
			<learnset_moves>
				<learnset_move>
					<name>Headbutt</name>
					<level>1</level>
				</learnset_move>
				<learnset_move>
					<name>Tackle</name>
					<level>1</level>
				</learnset_move>
				<learnset_move>
					<name>Tail Whip</name>
					<level>1</level>
				</learnset_move>
				<learnset_move>
					<name>Growl</name>
					<level>1</level>
				</learnset_move>
				<learnset_move>
					<name>Switcheroo</name>
					<level>1</level>
				</learnset_move>
				<learnset_move>
					<name>Tail Whip</name>
					<level>5</level>
				</learnset_move>
				<learnset_move>
					<name>Headbutt</name>
					<level>9</level>
				</learnset_move>
				<learnset_move>
					<name>Sand Attack</name>
					<level>13</level>
				</learnset_move>
				<learnset_move>
					<name>Odor Sleuth</name>
					<level>17</level>
				</learnset_move>
				<learnset_move>
					<name>Mud Sport</name>
					<level>23</level>
				</learnset_move>
				<learnset_move>
					<name>Fury Swipes</name>
					<level>29</level>
				</learnset_move>
				<learnset_move>
					<name>Covet</name>
					<level>35</level>
				</learnset_move>
				<learnset_move>
					<name>Slash</name>
					<level>41</level>
				</learnset_move>
				<learnset_move>
					<name>Rest</name>
					<level>47</level>
				</learnset_move>
				<learnset_move>
					<name>Belly Drum</name>
					<level>53</level>
				</learnset_move>
				<learnset_move>
					<name>Fling</name>
					<level>59</level>
				</learnset_move>
			</learnset_moves>
		</learnset>
		<learnset>
			<games>
				<game>Pokemon Black</game>
				<game>Pokemon White</game>
				<game>Pokemon Black 2</game>
				<game>Pokemon White 2</game>
			</games>
			<learnset_moves>
				<learnset_move>
					<name>Headbutt</name>
					<level>1</level>
				</learnset_move>
				<learnset_move>
					<name>Tackle</name>
					<level>1</level>
				</learnset_move>
				<learnset_move>
					<name>Tail Whip</name>
					<level>1</level>
				</learnset_move>
				<learnset_move>
					<name>Growl</name>
					<level>1</level>
				</learnset_move>
				<learnset_move>
					<name>Switcheroo</name>
					<level>1</level>
				</learnset_move>
				<learnset_move>
					<name>Tail Whip</name>
					<level>5</level>
				</learnset_move>
				<learnset_move>
					<name>Headbutt</name>
					<level>9</level>
				</learnset_move>
				<learnset_move>
					<name>Sand Attack</name>
					<level>13</level>
				</learnset_move>
				<learnset_move>
					<name>Odor Sleuth</name>
					<level>17</level>
				</learnset_move>
				<learnset_move>
					<name>Mud Sport</name>
					<level>23</level>
				</learnset_move>
				<learnset_move>
					<name>Fury Swipes</name>
					<level>29</level>
				</learnset_move>
				<learnset_move>
					<name>Covet</name>
					<level>35</level>
				</learnset_move>
				<learnset_move>
					<name>Bestow</name>
					<level>41</level>
				</learnset_move>
				<learnset_move>
					<name>Slash</name>
					<level>47</level>
				</learnset_move>
				<learnset_move>
					<name>Rest</name>
					<level>53</level>
				</learnset_move>
				<learnset_move>
					<name>Belly Drum</name>
					<level>59</level>
				</learnset_move>
				<learnset_move>
					<name>Fling</name>
					<level>65</level>
				</learnset_move>
			</learnset_moves>
		</learnset>
		<learnset>
			<games>
				<game>Pokemon X</game>
				<game>Pokemon Y</game>
			</games>
			<learnset_moves>
				<learnset_move>
					<name>Headbutt</name>
					<level>1</level>
				</learnset_move>
				<learnset_move>
					<name>Tackle</name>
					<level>1</level>
				</learnset_move>
				<learnset_move>
					<name>Tail Whip</name>
					<level>1</level>
				</learnset_move>
				<learnset_move>
					<name>Growl</name>
					<level>1</level>
				</learnset_move>
				<learnset_move>
					<name>Switcheroo</name>
					<level>1</level>
				</learnset_move>
				<learnset_move>
					<name>Rototiller</name>
					<level>1</level>
				</learnset_move>
				<learnset_move>
					<name>Play Rough</name>
					<level>1</level>
				</learnset_move>
				<learnset_move>
					<name>Tail Whip</name>
					<level>5</level>
				</learnset_move>
				<learnset_move>
					<name>Headbutt</name>
					<level>9</level>
				</learnset_move>
				<learnset_move>
					<name>Sand Attack</name>
					<level>13</level>
				</learnset_move>
				<learnset_move>
					<name>Odor Sleuth</name>
					<level>17</level>
				</learnset_move>
				<learnset_move>
					<name>Mud Sport</name>
					<level>23</level>
				</learnset_move>
				<learnset_move>
					<name>Fury Swipes</name>
					<level>29</level>
				</learnset_move>
				<learnset_move>
					<name>Covet</name>
					<level>35</level>
				</learnset_move>
				<learnset_move>
					<name>Bestow</name>
					<level>41</level>
				</learnset_move>
				<learnset_move>
					<name>Slash</name>
					<level>47</level>
				</learnset_move>
				<learnset_move>
					<name>Rest</name>
					<level>53</level>
				</learnset_move>
				<learnset_move>
					<name>Belly Drum</name>
					<level>59</level>
				</learnset_move>
				<learnset_move>
					<name>Fling</name>
					<level>65</level>
				</learnset_move>
			</learnset_moves>
		</learnset>
		<learnset>
			<games>
				<game>Pokemon Omega Ruby</game>
				<game>Pokemon Alpha Sapphire</game>
				<game>Pokemon Sun</game>
				<game>Pokemon Moon</game>
				<game>Pokemon Ultra Sun</game>
				<game>Pokemon Ultra Moon</game>
			</games>
			<learnset_moves>
				<learnset_move>
					<name>Sand Attack</name>
					<level>1</level>
				</learnset_move>
				<learnset_move>
					<name>Tackle</name>
					<level>1</level>
				</learnset_move>
				<learnset_move>
					<name>Tail Whip</name>
					<level>1</level>
				</learnset_move>
				<learnset_move>
					<name>Growl</name>
					<level>1</level>
				</learnset_move>
				<learnset_move>
					<name>Switcheroo</name>
					<level>1</level>
				</learnset_move>
				<learnset_move>
					<name>Rototiller</name>
					<level>1</level>
				</learnset_move>
				<learnset_move>
					<name>Play Rough</name>
					<level>1</level>
				</learnset_move>
				<learnset_move>
					<name>Tail Whip</name>
					<level>5</level>
				</learnset_move>
				<learnset_move>
					<name>Sand Attack</name>
					<level>7</level>
				</learnset_move>
				<learnset_move>
					<name>Headbutt</name>
					<level>11</level>
				</learnset_move>
				<learnset_move>
					<name>Odor Sleuth</name>
					<level>13</level>
				</learnset_move>
				<learnset_move>
					<name>Mud Sport</name>
					<level>17</level>
				</learnset_move>
				<learnset_move>
					<name>Fury Swipes</name>
					<level>19</level>
				</learnset_move>
				<learnset_move>
					<name>Covet</name>
					<level>24</level>
				</learnset_move>
				<learnset_move>
					<name>Bestow</name>
					<level>27</level>
				</learnset_move>
				<learnset_move>
					<name>Slash</name>
					<level>32</level>
				</learnset_move>
				<learnset_move>
					<name>Double Edge</name>
					<level>35</level>
				</learnset_move>
				<learnset_move>
					<name>Rest</name>
					<level>40</level>
				</learnset_move>
				<learnset_move>
					<name>Belly Drum</name>
					<level>43</level>
				</learnset_move>
				<learnset_move>
					<name>Fling</name>
					<level>48</level>
				</learnset_move>
			</learnset_moves>
		</learnset>
		<learnset>
			<games>
				<game>Pokemon Emerald Kaizo</game>
			</games>
			<learnset_moves>
				<learnset_move>
					<name>Facade</name>
					<level>1</level>
				</learnset_move>
				<learnset_move>
					<name>Slash</name>
					<level>1</level>
				</learnset_move>
				<learnset_move>
					<name>Sand Attack</name>
					<level>1</level>
				</learnset_move>
				<learnset_move>
					<name>Headbutt</name>
					<level>1</level>
				</learnset_move>
				<learnset_move>
					<name>Snore</name>
					<level>5</level>
				</learnset_move>
				<learnset_move>
					<name>Headbutt</name>
					<level>9</level>
				</learnset_move>
				<learnset_move>
					<name>Secret Power</name>
					<level>13</level>
				</learnset_move>
				<learnset_move>
					<name>Odor Sleuth</name>
					<level>17</level>
				</learnset_move>
				<learnset_move>
					<name>Dig</name>
					<level>29</level>
				</learnset_move>
				<learnset_move>
					<name>Body Slam</name>
					<level>35</level>
				</learnset_move>
				<learnset_move>
					<name>Shadow Ball</name>
					<level>41</level>
				</learnset_move>
				<learnset_move>
					<name>Double</name>
					<level>47</level>
				</learnset_move>
				<learnset_move>
					<name>Super Fang</name>
					<level>60</level>
				</learnset_move>
				<learnset_move>
					<name>Extremespeed</name>
					<level>73</level>
				</learnset_move>
			</learnset_moves>
		</learnset>
		<learnset>
			<games>
				<game>Pokemon Blaze Black</game>
				<game>Pokemon Volt White</game>
			</games>
			<learnset_moves>
				<learnset_move>
					<name>Headbutt</name>
					<level>1</level>
				</learnset_move>
				<learnset_move>
					<name>Tackle</name>
					<level>1</level>
				</learnset_move>
				<learnset_move>
					<name>Tail Whip</name>
					<level>1</level>
				</learnset_move>
				<learnset_move>
					<name>Growl</name>
					<level>1</level>
				</learnset_move>
				<learnset_move>
					<name>Switcheroo</name>
					<level>1</level>
				</learnset_move>
				<learnset_move>
					<name>Super Fang</name>
					<level>1</level>
				</learnset_move>
				<learnset_move>
					<name>Rock Climb</name>
					<level>1</level>
				</learnset_move>
				<learnset_move>
					<name>Tail Whip</name>
					<level>5</level>
				</learnset_move>
				<learnset_move>
					<name>Headbutt</name>
					<level>9</level>
				</learnset_move>
				<learnset_move>
					<name>Sand Attack</name>
					<level>13</level>
				</learnset_move>
				<learnset_move>
					<name>Odor Sleuth</name>
					<level>17</level>
				</learnset_move>
				<learnset_move>
					<name>ExtremeSpeed</name>
					<level>20</level>
				</learnset_move>
				<learnset_move>
					<name>Mud Sport</name>
					<level>23</level>
				</learnset_move>
				<learnset_move>
					<name>Fury Swipes</name>
					<level>29</level>
				</learnset_move>
				<learnset_move>
					<name>Covet</name>
					<level>35</level>
				</learnset_move>
				<learnset_move>
					<name>Bestow</name>
					<level>41</level>
				</learnset_move>
				<learnset_move>
					<name>Slash</name>
					<level>47</level>
				</learnset_move>
				<learnset_move>
					<name>Rest</name>
					<level>53</level>
				</learnset_move>
				<learnset_move>
					<name>Belly Drum</name>
					<level>59</level>
				</learnset_move>
				<learnset_move>
					<name>Fling</name>
					<level>65</level>
				</learnset_move>
			</learnset_moves>
		</learnset>
		<learnset>
			<games>
				<game>Pokemon Sword</game>
				<game>Pokemon Shield</game>
			</games>
			<learnset_moves>
				<learnset_move>
					<name>Slash</name>
					<level>1</level>
				</learnset_move>
				<learnset_move>
					<name>Slash</name>
					<level>1</level>
				</learnset_move>
				<learnset_move>
					<name>Switcheroo</name>
					<level>1</level>
				</learnset_move>
				<learnset_move>
					<name>Pin Missile</name>
					<level>1</level>
				</learnset_move>
				<learnset_move>
					<name>Tackle</name>
					<level>1</level>
				</learnset_move>
				<learnset_move>
					<name>Growl</name>
					<level>1</level>
				</learnset_move>
				<learnset_move>
					<name>Sand Attack</name>
					<level>1</level>
				</learnset_move>
				<learnset_move>
					<name>Tail Whip</name>
					<level>1</level>
				</learnset_move>
				<learnset_move>
					<name>Covet</name>
					<level>9</level>
				</learnset_move>
				<learnset_move>
					<name>Headbutt</name>
					<level>12</level>
				</learnset_move>
				<learnset_move>
					<name>Hone Claws</name>
					<level>15</level>
				</learnset_move>
				<learnset_move>
					<name>Fury Swipes</name>
					<level>18</level>
				</learnset_move>
				<learnset_move>
					<name>Rest</name>
					<level>23</level>
				</learnset_move>
				<learnset_move>
					<name>Take Down</name>
					<level>28</level>
				</learnset_move>
				<learnset_move>
					<name>Fling</name>
					<level>33</level>
				</learnset_move>
				<learnset_move>
					<name>Flail</name>
					<level>38</level>
				</learnset_move>
				<learnset_move>
					<name>Belly Drum</name>
					<level>43</level>
				</learnset_move>
			</learnset_moves>
		</learnset>
		<learnset>
			<games>
				<game>Pokemon Renegade Platinum</game>
			</games>
			<learnset_moves>
				<learnset_move>
					<name>Extreme Speed</name>
					<level>1</level>
				</learnset_move>
				<learnset_move>
					<name>Play Rough</name>
					<level>1</level>
				</learnset_move>
				<learnset_move>
					<name>Switcheroo</name>
					<level>1</level>
				</learnset_move>
				<learnset_move>
					<name>Tackle</name>
					<level>1</level>
				</learnset_move>
				<learnset_move>
					<name>Growl</name>
					<level>1</level>
				</learnset_move>
				<learnset_move>
					<name>Tail Whip</name>
					<level>1</level>
				</learnset_move>
				<learnset_move>
					<name>Sand Attack</name>
					<level>1</level>
				</learnset_move>
				<learnset_move>
					<name>Covet</name>
					<level>7</level>
				</learnset_move>
				<learnset_move>
					<name>Odor Sleuth</name>
					<level>10</level>
				</learnset_move>
				<learnset_move>
					<name>Headbutt</name>
					<level>13</level>
				</learnset_move>
				<learnset_move>
					<name>Fury Swipes</name>
					<level>16</level>
				</learnset_move>
				<learnset_move>
					<name>Mud Sport</name>
					<level>19</level>
				</learnset_move>
				<learnset_move>
					<name>Slash</name>
					<level>23</level>
				</learnset_move>
				<learnset_move>
					<name>Take Down</name>
					<level>27</level>
				</learnset_move>
				<learnset_move>
					<name>Rest</name>
					<level>31</level>
				</learnset_move>
				<learnset_move>
					<name>Double-Edge</name>
					<level>35</level>
				</learnset_move>
				<learnset_move>
					<name>Belly Drum</name>
					<level>39</level>
				</learnset_move>
				<learnset_move>
					<name>Fling</name>
					<level>43</level>
				</learnset_move>
				<learnset_move>
					<name>Super Fang</name>
					<level>47</level>
				</learnset_move>
				<learnset_move>
					<name>Extreme Speed</name>
					<level>51</level>
				</learnset_move>
			</learnset_moves>
		</learnset>
	</learnsets>
</pokemon_learnsets>
