<?xml version='1.0' encoding='utf-8' standalone='no'?>
<pokemon_learnsets>
	<name>Mothim</name>
	<learnsets>
		<learnset>
			<games>
				<game>Pokemon Diamond</game>
				<game>Pokemon Pearl</game>
			</games>
			<learnset_moves>
				<learnset_move>
					<name>Tackle</name>
					<level>1</level>
				</learnset_move>
				<learnset_move>
					<name>Protect</name>
					<level>10</level>
				</learnset_move>
				<learnset_move>
					<name>Hidden Power</name>
					<level>20</level>
				</learnset_move>
				<learnset_move>
					<name>Confusion</name>
					<level>23</level>
				</learnset_move>
				<learnset_move>
					<name>Gust</name>
					<level>26</level>
				</learnset_move>
				<learnset_move>
					<name>Poison Powder</name>
					<level>29</level>
				</learnset_move>
				<learnset_move>
					<name>Psybeam</name>
					<level>32</level>
				</learnset_move>
				<learnset_move>
					<name>Camouflage</name>
					<level>35</level>
				</learnset_move>
				<learnset_move>
					<name>Silver Wind</name>
					<level>38</level>
				</learnset_move>
				<learnset_move>
					<name>Air Slash</name>
					<level>41</level>
				</learnset_move>
				<learnset_move>
					<name>Psychic</name>
					<level>44</level>
				</learnset_move>
				<learnset_move>
					<name>Bug Buzz</name>
					<level>47</level>
				</learnset_move>
			</learnset_moves>
		</learnset>
		<learnset>
			<games>
				<game>Pokemon Platinum</game>
				<game>Pokemon HeartGold</game>
				<game>Pokemon SoulSilver</game>
			</games>
			<learnset_moves>
				<learnset_move>
					<name>Tackle</name>
					<level>1</level>
				</learnset_move>
				<learnset_move>
					<name>Protect</name>
					<level>10</level>
				</learnset_move>
				<learnset_move>
					<name>Bug Bite</name>
					<level>15</level>
				</learnset_move>
				<learnset_move>
					<name>Hidden Power</name>
					<level>20</level>
				</learnset_move>
				<learnset_move>
					<name>Confusion</name>
					<level>23</level>
				</learnset_move>
				<learnset_move>
					<name>Gust</name>
					<level>26</level>
				</learnset_move>
				<learnset_move>
					<name>Poison Powder</name>
					<level>29</level>
				</learnset_move>
				<learnset_move>
					<name>Psybeam</name>
					<level>32</level>
				</learnset_move>
				<learnset_move>
					<name>Camouflage</name>
					<level>35</level>
				</learnset_move>
				<learnset_move>
					<name>Silver Wind</name>
					<level>38</level>
				</learnset_move>
				<learnset_move>
					<name>Air Slash</name>
					<level>41</level>
				</learnset_move>
				<learnset_move>
					<name>Psychic</name>
					<level>44</level>
				</learnset_move>
				<learnset_move>
					<name>Bug Buzz</name>
					<level>47</level>
				</learnset_move>
			</learnset_moves>
		</learnset>
		<learnset>
			<games>
				<game>Pokemon Black</game>
				<game>Pokemon White</game>
				<game>Pokemon Black 2</game>
				<game>Pokemon White 2</game>
				<game>Pokemon X</game>
				<game>Pokemon Y</game>
				<game>Pokemon Omega Ruby</game>
				<game>Pokemon Alpha Sapphire</game>
			</games>
			<learnset_moves>
				<learnset_move>
					<name>Tackle</name>
					<level>1</level>
				</learnset_move>
				<learnset_move>
					<name>Protect</name>
					<level>10</level>
				</learnset_move>
				<learnset_move>
					<name>Bug Bite</name>
					<level>15</level>
				</learnset_move>
				<learnset_move>
					<name>Hidden Power</name>
					<level>20</level>
				</learnset_move>
				<learnset_move>
					<name>Confusion</name>
					<level>23</level>
				</learnset_move>
				<learnset_move>
					<name>Gust</name>
					<level>26</level>
				</learnset_move>
				<learnset_move>
					<name>Poison Powder</name>
					<level>29</level>
				</learnset_move>
				<learnset_move>
					<name>Psybeam</name>
					<level>32</level>
				</learnset_move>
				<learnset_move>
					<name>Camouflage</name>
					<level>35</level>
				</learnset_move>
				<learnset_move>
					<name>Silver Wind</name>
					<level>38</level>
				</learnset_move>
				<learnset_move>
					<name>Air Slash</name>
					<level>41</level>
				</learnset_move>
				<learnset_move>
					<name>Psychic</name>
					<level>44</level>
				</learnset_move>
				<learnset_move>
					<name>Bug Buzz</name>
					<level>47</level>
				</learnset_move>
				<learnset_move>
					<name>Quiver Dance</name>
					<level>50</level>
				</learnset_move>
			</learnset_moves>
		</learnset>
		<learnset>
			<games>
				<game>Pokemon Sun</game>
				<game>Pokemon Moon</game>
				<game>Pokemon Ultra Sun</game>
				<game>Pokemon Ultra Moon</game>
			</games>
			<learnset_moves>
				<learnset_move>
					<name>Tackle</name>
					<level>1</level>
				</learnset_move>
				<learnset_move>
					<name>Protect</name>
					<level>1</level>
				</learnset_move>
				<learnset_move>
					<name>Bug Bite</name>
					<level>1</level>
				</learnset_move>
				<learnset_move>
					<name>Quiver Dance</name>
					<level>1</level>
				</learnset_move>
				<learnset_move>
					<name>Protect</name>
					<level>10</level>
				</learnset_move>
				<learnset_move>
					<name>Bug Bite</name>
					<level>15</level>
				</learnset_move>
				<learnset_move>
					<name>Hidden Power</name>
					<level>20</level>
				</learnset_move>
				<learnset_move>
					<name>Confusion</name>
					<level>23</level>
				</learnset_move>
				<learnset_move>
					<name>Gust</name>
					<level>26</level>
				</learnset_move>
				<learnset_move>
					<name>Poison Powder</name>
					<level>29</level>
				</learnset_move>
				<learnset_move>
					<name>Psybeam</name>
					<level>32</level>
				</learnset_move>
				<learnset_move>
					<name>Camouflage</name>
					<level>35</level>
				</learnset_move>
				<learnset_move>
					<name>Silver Wind</name>
					<level>38</level>
				</learnset_move>
				<learnset_move>
					<name>Air Slash</name>
					<level>41</level>
				</learnset_move>
				<learnset_move>
					<name>Psychic</name>
					<level>44</level>
				</learnset_move>
				<learnset_move>
					<name>Lunge</name>
					<level>47</level>
				</learnset_move>
				<learnset_move>
					<name>Bug Buzz</name>
					<level>50</level>
				</learnset_move>
			</learnset_moves>
		</learnset>
		<learnset>
			<games>
				<game>Pokemon Blaze Black</game>
				<game>Pokemon Volt White</game>
			</games>
			<learnset_moves>
				<learnset_move>
					<name>Tackle</name>
					<level>1</level>
				</learnset_move>
				<learnset_move>
					<name>Giga Drain</name>
					<level>1</level>
				</learnset_move>
				<learnset_move>
					<name>Protect</name>
					<level>10</level>
				</learnset_move>
				<learnset_move>
					<name>Bug Bite</name>
					<level>15</level>
				</learnset_move>
				<learnset_move>
					<name>Hidden Power</name>
					<level>20</level>
				</learnset_move>
				<learnset_move>
					<name>Air Cutter</name>
					<level>20</level>
				</learnset_move>
				<learnset_move>
					<name>Confusion</name>
					<level>23</level>
				</learnset_move>
				<learnset_move>
					<name>Gust</name>
					<level>26</level>
				</learnset_move>
				<learnset_move>
					<name>Poison Powder</name>
					<level>29</level>
				</learnset_move>
				<learnset_move>
					<name>Psybeam</name>
					<level>32</level>
				</learnset_move>
				<learnset_move>
					<name>Camouflage</name>
					<level>35</level>
				</learnset_move>
				<learnset_move>
					<name>Silver Wind</name>
					<level>38</level>
				</learnset_move>
				<learnset_move>
					<name>Air Slash</name>
					<level>41</level>
				</learnset_move>
				<learnset_move>
					<name>Psychic</name>
					<level>44</level>
				</learnset_move>
				<learnset_move>
					<name>Bug Buzz</name>
					<level>47</level>
				</learnset_move>
				<learnset_move>
					<name>Quiver Dance</name>
					<level>50</level>
				</learnset_move>
				<learnset_move>
					<name>Hurricane</name>
					<level>53</level>
				</learnset_move>
			</learnset_moves>
		</learnset>
		<learnset>
			<games>
				<game>Pokemon Renegade Platinum</game>
			</games>
			<learnset_moves>
				<learnset_move>
					<name>Hurricane </name>
					<level>1</level>
				</learnset_move>
				<learnset_move>
					<name>Protect</name>
					<level>1</level>
				</learnset_move>
				<learnset_move>
					<name>Tackle</name>
					<level>1</level>
				</learnset_move>
				<learnset_move>
					<name>Bug Bite</name>
					<level>1</level>
				</learnset_move>
				<learnset_move>
					<name>Hidden Power</name>
					<level>1</level>
				</learnset_move>
				<learnset_move>
					<name>Gust</name>
					<level>20</level>
				</learnset_move>
				<learnset_move>
					<name>Confusion</name>
					<level>23</level>
				</learnset_move>
				<learnset_move>
					<name>Bug Buzz</name>
					<level>26</level>
				</learnset_move>
				<learnset_move>
					<name>Poison Powder</name>
					<level>29</level>
				</learnset_move>
				<learnset_move>
					<name>Air Cutter</name>
					<level>32</level>
				</learnset_move>
				<learnset_move>
					<name>Psybeam</name>
					<level>35</level>
				</learnset_move>
				<learnset_move>
					<name>Air Slash</name>
					<level>38</level>
				</learnset_move>
				<learnset_move>
					<name>Psychic</name>
					<level>41</level>
				</learnset_move>
				<learnset_move>
					<name>Flail</name>
					<level>44</level>
				</learnset_move>
				<learnset_move>
					<name>Camouflage</name>
					<level>47</level>
				</learnset_move>
				<learnset_move>
					<name>Hurricane </name>
					<level>50</level>
				</learnset_move>
			</learnset_moves>
		</learnset>
		<learnset>
			<games>
				<game>Pokemon Blaze Black 2</game>
				<game>Pokemon Volt White 2</game>
			</games>
			<learnset_moves>
				<learnset_move>
					<name>Tackle</name>
					<level>1</level>
				</learnset_move>
				<learnset_move>
					<name>Giga Drain</name>
					<level>1</level>
				</learnset_move>
				<learnset_move>
					<name>Protect</name>
					<level>10</level>
				</learnset_move>
				<learnset_move>
					<name>Bug Bite</name>
					<level>15</level>
				</learnset_move>
				<learnset_move>
					<name>Hidden Power</name>
					<level>20</level>
				</learnset_move>
				<learnset_move>
					<name>Air Cutter</name>
					<level>20</level>
				</learnset_move>
				<learnset_move>
					<name>Confusion</name>
					<level>23</level>
				</learnset_move>
				<learnset_move>
					<name>Gust</name>
					<level>26</level>
				</learnset_move>
				<learnset_move>
					<name>Poison Powder</name>
					<level>29</level>
				</learnset_move>
				<learnset_move>
					<name>Psybeam</name>
					<level>32</level>
				</learnset_move>
				<learnset_move>
					<name>Camouflage</name>
					<level>35</level>
				</learnset_move>
				<learnset_move>
					<name>Silver Wind</name>
					<level>38</level>
				</learnset_move>
				<learnset_move>
					<name>Air Slash</name>
					<level>41</level>
				</learnset_move>
				<learnset_move>
					<name>Psychic</name>
					<level>44</level>
				</learnset_move>
				<learnset_move>
					<name>Bug Buzz</name>
					<level>47</level>
				</learnset_move>
				<learnset_move>
					<name>Quiver Dance</name>
					<level>50</level>
				</learnset_move>
				<learnset_move>
					<name>Hurricane</name>
					<level>53</level>
				</learnset_move>
			</learnset_moves>
		</learnset>
		<learnset>
			<games>
				<game>Pokemon Brilliant Diamond</game>
				<game>Pokemon Shining Pearl</game>
			</games>
			<learnset_moves>
				<learnset_move>
					<name>Quiver Dance</name>
					<level>1</level>
				</learnset_move>
				<learnset_move>
					<name>Quiver Dance</name>
					<level>1</level>
				</learnset_move>
				<learnset_move>
					<name>Tackle</name>
					<level>1</level>
				</learnset_move>
				<learnset_move>
					<name>Protect</name>
					<level>1</level>
				</learnset_move>
				<learnset_move>
					<name>Bug Bite</name>
					<level>1</level>
				</learnset_move>
				<learnset_move>
					<name>Protect</name>
					<level>10</level>
				</learnset_move>
				<learnset_move>
					<name>Bug Bite</name>
					<level>15</level>
				</learnset_move>
				<learnset_move>
					<name>String Shot</name>
					<level>20</level>
				</learnset_move>
				<learnset_move>
					<name>Confusion</name>
					<level>23</level>
				</learnset_move>
				<learnset_move>
					<name>Gust</name>
					<level>26</level>
				</learnset_move>
				<learnset_move>
					<name>Poison Powder</name>
					<level>29</level>
				</learnset_move>
				<learnset_move>
					<name>Psybeam</name>
					<level>32</level>
				</learnset_move>
				<learnset_move>
					<name>Roost</name>
					<level>35</level>
				</learnset_move>
				<learnset_move>
					<name>Struggle Bug</name>
					<level>38</level>
				</learnset_move>
				<learnset_move>
					<name>Air Slash</name>
					<level>41</level>
				</learnset_move>
				<learnset_move>
					<name>Psychic</name>
					<level>44</level>
				</learnset_move>
				<learnset_move>
					<name>Lunge</name>
					<level>47</level>
				</learnset_move>
				<learnset_move>
					<name>Bug Buzz</name>
					<level>50</level>
				</learnset_move>
			</learnset_moves>
		</learnset>
	</learnsets>
</pokemon_learnsets>
