<?xml version='1.0' encoding='utf-8' standalone='no'?>
<pokemon_learnsets>
	<name>Shedinja</name>
	<learnsets>
		<learnset>
			<games>
				<game>Pokemon Ruby</game>
				<game>Pokemon Sapphire</game>
				<game>Pokemon Emerald</game>
				<game>Pokemon FireRed</game>
				<game>Pokemon LeafGreen</game>
			</games>
			<learnset_moves>
				<learnset_move>
					<name>Scratch</name>
					<level>1</level>
				</learnset_move>
				<learnset_move>
					<name>Harden</name>
					<level>1</level>
				</learnset_move>
				<learnset_move>
					<name>Leech Life</name>
					<level>5</level>
				</learnset_move>
				<learnset_move>
					<name>Sand Attack</name>
					<level>9</level>
				</learnset_move>
				<learnset_move>
					<name>Fury Swipes</name>
					<level>14</level>
				</learnset_move>
				<learnset_move>
					<name>Mind Reader</name>
					<level>19</level>
				</learnset_move>
				<learnset_move>
					<name>Spite</name>
					<level>25</level>
				</learnset_move>
				<learnset_move>
					<name>Confuse Ray</name>
					<level>31</level>
				</learnset_move>
				<learnset_move>
					<name>Shadow Ball</name>
					<level>38</level>
				</learnset_move>
				<learnset_move>
					<name>Grudge</name>
					<level>45</level>
				</learnset_move>
			</learnset_moves>
		</learnset>
		<learnset>
			<games>
				<game>Pokemon Diamond</game>
				<game>Pokemon Pearl</game>
				<game>Pokemon Platinum</game>
				<game>Pokemon HeartGold</game>
				<game>Pokemon SoulSilver</game>
				<game>Pokemon Black</game>
				<game>Pokemon White</game>
				<game>Pokemon Black 2</game>
				<game>Pokemon White 2</game>
			</games>
			<learnset_moves>
				<learnset_move>
					<name>Scratch</name>
					<level>1</level>
				</learnset_move>
				<learnset_move>
					<name>Harden</name>
					<level>1</level>
				</learnset_move>
				<learnset_move>
					<name>Leech Life</name>
					<level>5</level>
				</learnset_move>
				<learnset_move>
					<name>Sand Attack</name>
					<level>9</level>
				</learnset_move>
				<learnset_move>
					<name>Fury Swipes</name>
					<level>14</level>
				</learnset_move>
				<learnset_move>
					<name>Mind Reader</name>
					<level>19</level>
				</learnset_move>
				<learnset_move>
					<name>Spite</name>
					<level>25</level>
				</learnset_move>
				<learnset_move>
					<name>Confuse Ray</name>
					<level>31</level>
				</learnset_move>
				<learnset_move>
					<name>Shadow Sneak</name>
					<level>38</level>
				</learnset_move>
				<learnset_move>
					<name>Grudge</name>
					<level>45</level>
				</learnset_move>
				<learnset_move>
					<name>Heal Block</name>
					<level>52</level>
				</learnset_move>
				<learnset_move>
					<name>Shadow Ball</name>
					<level>59</level>
				</learnset_move>
			</learnset_moves>
		</learnset>
		<learnset>
			<games>
				<game>Pokemon X</game>
				<game>Pokemon Y</game>
			</games>
			<learnset_moves>
				<learnset_move>
					<name>Scratch</name>
					<level>1</level>
				</learnset_move>
				<learnset_move>
					<name>Harden</name>
					<level>1</level>
				</learnset_move>
				<learnset_move>
					<name>Leech Life</name>
					<level>5</level>
				</learnset_move>
				<learnset_move>
					<name>Sand Attack</name>
					<level>9</level>
				</learnset_move>
				<learnset_move>
					<name>Fury Swipes</name>
					<level>14</level>
				</learnset_move>
				<learnset_move>
					<name>Mind Reader</name>
					<level>19</level>
				</learnset_move>
				<learnset_move>
					<name>Spite</name>
					<level>25</level>
				</learnset_move>
				<learnset_move>
					<name>Confuse Ray</name>
					<level>31</level>
				</learnset_move>
				<learnset_move>
					<name>Shadow Sneak</name>
					<level>38</level>
				</learnset_move>
				<learnset_move>
					<name>Grudge</name>
					<level>43</level>
				</learnset_move>
				<learnset_move>
					<name>Phantom Force</name>
					<level>47</level>
				</learnset_move>
				<learnset_move>
					<name>Heal Block</name>
					<level>50</level>
				</learnset_move>
				<learnset_move>
					<name>Shadow Ball</name>
					<level>59</level>
				</learnset_move>
			</learnset_moves>
		</learnset>
		<learnset>
			<games>
				<game>Pokemon Omega Ruby</game>
				<game>Pokemon Alpha Sapphire</game>
			</games>
			<learnset_moves>
				<learnset_move>
					<name>Scratch</name>
					<level>1</level>
				</learnset_move>
				<learnset_move>
					<name>Harden</name>
					<level>1</level>
				</learnset_move>
				<learnset_move>
					<name>Leech Life</name>
					<level>5</level>
				</learnset_move>
				<learnset_move>
					<name>Sand Attack</name>
					<level>9</level>
				</learnset_move>
				<learnset_move>
					<name>Fury Swipes</name>
					<level>13</level>
				</learnset_move>
				<learnset_move>
					<name>Spite</name>
					<level>17</level>
				</learnset_move>
				<learnset_move>
					<name>Shadow Sneak</name>
					<level>21</level>
				</learnset_move>
				<learnset_move>
					<name>Mind Reader</name>
					<level>25</level>
				</learnset_move>
				<learnset_move>
					<name>Confuse Ray</name>
					<level>29</level>
				</learnset_move>
				<learnset_move>
					<name>Shadow Ball</name>
					<level>33</level>
				</learnset_move>
				<learnset_move>
					<name>Grudge</name>
					<level>37</level>
				</learnset_move>
				<learnset_move>
					<name>Heal Block</name>
					<level>41</level>
				</learnset_move>
				<learnset_move>
					<name>Phantom Force</name>
					<level>45</level>
				</learnset_move>
			</learnset_moves>
		</learnset>
		<learnset>
			<games>
				<game>Pokemon Sun</game>
				<game>Pokemon Moon</game>
				<game>Pokemon Ultra Sun</game>
				<game>Pokemon Ultra Moon</game>
			</games>
			<learnset_moves>
				<learnset_move>
					<name>Scratch</name>
					<level>1</level>
				</learnset_move>
				<learnset_move>
					<name>Sand Attack</name>
					<level>1</level>
				</learnset_move>
				<learnset_move>
					<name>Absorb</name>
					<level>1</level>
				</learnset_move>
				<learnset_move>
					<name>Harden</name>
					<level>1</level>
				</learnset_move>
				<learnset_move>
					<name>Absorb</name>
					<level>5</level>
				</learnset_move>
				<learnset_move>
					<name>Sand Attack</name>
					<level>9</level>
				</learnset_move>
				<learnset_move>
					<name>Fury Swipes</name>
					<level>13</level>
				</learnset_move>
				<learnset_move>
					<name>Spite</name>
					<level>17</level>
				</learnset_move>
				<learnset_move>
					<name>Shadow Sneak</name>
					<level>21</level>
				</learnset_move>
				<learnset_move>
					<name>Mind Reader</name>
					<level>25</level>
				</learnset_move>
				<learnset_move>
					<name>Confuse Ray</name>
					<level>29</level>
				</learnset_move>
				<learnset_move>
					<name>Shadow Ball</name>
					<level>33</level>
				</learnset_move>
				<learnset_move>
					<name>Grudge</name>
					<level>37</level>
				</learnset_move>
				<learnset_move>
					<name>Heal Block</name>
					<level>41</level>
				</learnset_move>
				<learnset_move>
					<name>Phantom Force</name>
					<level>45</level>
				</learnset_move>
			</learnset_moves>
		</learnset>
		<learnset>
			<games>
				<game>Pokemon Renegade Platinum</game>
			</games>
			<learnset_moves>
				<learnset_move>
					<name>Scratch</name>
					<level>1</level>
				</learnset_move>
				<learnset_move>
					<name>Harden</name>
					<level>1</level>
				</learnset_move>
				<learnset_move>
					<name>Absorb</name>
					<level>1</level>
				</learnset_move>
				<learnset_move>
					<name>Bug Bite</name>
					<level>1</level>
				</learnset_move>
				<learnset_move>
					<name>Sand Attack</name>
					<level>4</level>
				</learnset_move>
				<learnset_move>
					<name>Fury Swipes</name>
					<level>7</level>
				</learnset_move>
				<learnset_move>
					<name>Spite</name>
					<level>11</level>
				</learnset_move>
				<learnset_move>
					<name>Leech Life</name>
					<level>15</level>
				</learnset_move>
				<learnset_move>
					<name>Mind Reader</name>
					<level>19</level>
				</learnset_move>
				<learnset_move>
					<name>Shadow Sneak</name>
					<level>23</level>
				</learnset_move>
				<learnset_move>
					<name>X-Scissor</name>
					<level>27</level>
				</learnset_move>
				<learnset_move>
					<name>Confuse Ray</name>
					<level>31</level>
				</learnset_move>
				<learnset_move>
					<name>Shadow Ball</name>
					<level>35</level>
				</learnset_move>
				<learnset_move>
					<name>Heal Block</name>
					<level>39</level>
				</learnset_move>
				<learnset_move>
					<name>Grudge</name>
					<level>43</level>
				</learnset_move>
			</learnset_moves>
		</learnset>
		<learnset>
			<games>
				<game>Pokemon Sword</game>
				<game>Pokemon Shield</game>
				<game>Pokemon Brilliant Diamond</game>
				<game>Pokemon Shining Pearl</game>
			</games>
			<learnset_moves>
				<learnset_move>
					<name>Shadow Claw</name>
					<level>1</level>
				</learnset_move>
				<learnset_move>
					<name>Grudge</name>
					<level>1</level>
				</learnset_move>
				<learnset_move>
					<name>Mud-Slap</name>
					<level>1</level>
				</learnset_move>
				<learnset_move>
					<name>Metal Claw</name>
					<level>1</level>
				</learnset_move>
				<learnset_move>
					<name>Dig</name>
					<level>1</level>
				</learnset_move>
				<learnset_move>
					<name>Scratch</name>
					<level>1</level>
				</learnset_move>
				<learnset_move>
					<name>Sand Attack</name>
					<level>1</level>
				</learnset_move>
				<learnset_move>
					<name>Harden</name>
					<level>1</level>
				</learnset_move>
				<learnset_move>
					<name>False Swipe</name>
					<level>1</level>
				</learnset_move>
				<learnset_move>
					<name>Confuse Ray</name>
					<level>15</level>
				</learnset_move>
				<learnset_move>
					<name>Absorb</name>
					<level>23</level>
				</learnset_move>
				<learnset_move>
					<name>Shadow Sneak</name>
					<level>29</level>
				</learnset_move>
				<learnset_move>
					<name>Fury Swipes</name>
					<level>36</level>
				</learnset_move>
				<learnset_move>
					<name>Mind Reader</name>
					<level>43</level>
				</learnset_move>
				<learnset_move>
					<name>Shadow Ball</name>
					<level>50</level>
				</learnset_move>
				<learnset_move>
					<name>Spite</name>
					<level>57</level>
				</learnset_move>
				<learnset_move>
					<name>Phantom Force</name>
					<level>64</level>
				</learnset_move>
			</learnset_moves>
		</learnset>
		<learnset>
			<games>
				<game>Pokemon Emerald Kaizo</game>
			</games>
			<learnset_moves>
				<learnset_move>
					<name>Signal Beam</name>
					<level>1</level>
				</learnset_move>
				<learnset_move>
					<name>Leech Life</name>
					<level>1</level>
				</learnset_move>
				<learnset_move>
					<name>Take Down</name>
					<level>5</level>
				</learnset_move>
				<learnset_move>
					<name>Sand Attack</name>
					<level>9</level>
				</learnset_move>
				<learnset_move>
					<name>Confuse Ray</name>
					<level>14</level>
				</learnset_move>
				<learnset_move>
					<name>Silver Wind</name>
					<level>19</level>
				</learnset_move>
				<learnset_move>
					<name>Double-Edge</name>
					<level>25</level>
				</learnset_move>
				<learnset_move>
					<name>Shadow Sneak</name>
					<level>31</level>
				</learnset_move>
				<learnset_move>
					<name>Shadow Ball</name>
					<level>38</level>
				</learnset_move>
				<learnset_move>
					<name>X-Scissors</name>
					<level>45</level>
				</learnset_move>
			</learnset_moves>
		</learnset>
		<learnset>
			<games>
				<game>Pokemon Blaze Black 2 Redux</game>
				<game>Pokemon Volt White 2 Redux</game>
			</games>
			<learnset_moves>
				<learnset_move>
					<name>Sucker Punch</name>
					<level>1</level>
				</learnset_move>
				<learnset_move>
					<name>Absorb</name>
					<level>1</level>
				</learnset_move>
				<learnset_move>
					<name>Scratch</name>
					<level>1</level>
				</learnset_move>
				<learnset_move>
					<name>Sand Attack</name>
					<level>4</level>
				</learnset_move>
				<learnset_move>
					<name>Fury Swipes</name>
					<level>6</level>
				</learnset_move>
				<learnset_move>
					<name>String Shot</name>
					<level>8</level>
				</learnset_move>
				<learnset_move>
					<name>Mud-Slap</name>
					<level>10</level>
				</learnset_move>
				<learnset_move>
					<name>Bug Bite</name>
					<level>12</level>
				</learnset_move>
				<learnset_move>
					<name>Gust</name>
					<level>14</level>
				</learnset_move>
				<learnset_move>
					<name>Fury Cutter</name>
					<level>16</level>
				</learnset_move>
				<learnset_move>
					<name>Metal Claw</name>
					<level>18</level>
				</learnset_move>
				<learnset_move>
					<name>Struggle Bug</name>
					<level>20</level>
				</learnset_move>
				<learnset_move>
					<name>Final Gambit</name>
					<level>20</level>
				</learnset_move>
				<learnset_move>
					<name>Trick</name>
					<level>24</level>
				</learnset_move>
				<learnset_move>
					<name>Shadow Sneak</name>
					<level>28</level>
				</learnset_move>
				<learnset_move>
					<name>Lunge</name>
					<level>32</level>
				</learnset_move>
				<learnset_move>
					<name>Heal Block</name>
					<level>36</level>
				</learnset_move>
				<learnset_move>
					<name>Hone Claws</name>
					<level>40</level>
				</learnset_move>
				<learnset_move>
					<name>Screech</name>
					<level>44</level>
				</learnset_move>
				<learnset_move>
					<name>Slash</name>
					<level>48</level>
				</learnset_move>
				<learnset_move>
					<name>Night Slash</name>
					<level>48</level>
				</learnset_move>
				<learnset_move>
					<name>Mind Reader</name>
					<level>52</level>
				</learnset_move>
				<learnset_move>
					<name>Ally Switch</name>
					<level>56</level>
				</learnset_move>
				<learnset_move>
					<name>Leech Life</name>
					<level>60</level>
				</learnset_move>
				<learnset_move>
					<name>Grudge</name>
					<level>64</level>
				</learnset_move>
			</learnset_moves>
		</learnset>
	</learnsets>
</pokemon_learnsets>
